jsonpack/__init__.py
jsonpack/exceptions.py
jsonpack/node.py
jsonpack/util.py
jsonpack-0.0.1.dist-info/LICENSE
jsonpack-0.0.1.dist-info/METADATA
jsonpack-0.0.1.dist-info/WHEEL
jsonpack-0.0.1.dist-info/top_level.txt
jsonpack-0.0.1.dist-info/RECORD
