Metadata-Version: 2.1
Name: jsonpack
Version: 0.0.1
Summary: Easily create JSON packs for your Python Application.
Home-page: https://github.com/legopitstop/jsonpack
Author: Legopitstop
Author-email: officiallegopitstop@gmail.com
License: MIT
Keywords: json,pack,manifest,scripts,events,components,Pillow
Classifier: Development Status :: 4 - Beta
Classifier: Intended Audience :: Developers
Classifier: Topic :: Software Development :: Build Tools
Classifier: License :: OSI Approved :: MIT License
Classifier: Operating System :: Microsoft :: Windows
Classifier: Programming Language :: Python :: 3.9
Requires-Python: >=3.6
License-File: LICENSE
